m0deler/__init__.py
m0deler/m0deler.py
m0deler/monte.py
m0deler/server_core.py
m0deler/transaction.py
pym0deler/__init__.py
pym0deler/m0deler.py
pym0deler/monte.py
pym0deler/server_core.py
pym0deler/transaction.py
m0deler_python-0.2.dist-info/METADATA
m0deler_python-0.2.dist-info/WHEEL
m0deler_python-0.2.dist-info/top_level.txt
m0deler_python-0.2.dist-info/RECORD
