Metadata-Version: 2.1
Name: m0deler-python
Version: 0.2
Author: Chainhaus
Requires-Dist: pandas
Requires-Dist: matplotlib
Requires-Dist: datetime
Requires-Dist: requests
Requires-Dist: numpy
Requires-Dist: chart-studio
Requires-Dist: plotly
